rx_scheduler/__init__.py
rx_scheduler/scheduler.py
rx_scheduler/task.py
tests/__init__.py
rx_scheduler-0.0.1.dist-info/LICENSE
rx_scheduler-0.0.1.dist-info/METADATA
rx_scheduler-0.0.1.dist-info/WHEEL
rx_scheduler-0.0.1.dist-info/top_level.txt
rx_scheduler-0.0.1.dist-info/RECORD
