Metadata-Version: 2.1
Name: rx-scheduler
Version: 0.0.1
Summary: Function interval runner based on rxpy and asyncio
Home-page: https://github.com/ryazantseff/rxpy-scheduler
Author: Maxim Ryazantsev
Author-email: maxim.ryazancev@gmail.com
License: MIT
Keywords: Scheduler,rxpy,async
Platform: UNKNOWN
Classifier: Development Status :: 3 - Alpha
Classifier: Intended Audience :: Developers
Classifier: Topic :: Software Development :: Build Tools
Classifier: License :: OSI Approved :: MIT License
Classifier: Programming Language :: Python :: 3.8
Classifier: Programming Language :: Python :: 3.9
Requires-Dist: asyncio
Requires-Dist: rx
